{"nodes": [{"id": "typesindex_transaction", "label": "Transaction type", "file_type": "code", "source_file": "src/types/index.ts", "source_location": "112", "source_url": null, "captured_at": null, "author": null, "contributor": null}, {"id": "typesindex_invoice", "label": "Invoice type", "file_type": "code", "source_file": "src/types/index.ts", "source_location": "136", "source_url": null, "captured_at": null, "author": null, "contributor": null}, {"id": "typesindex_goal", "label": "Goal type", "file_type": "code", "source_file": "src/types/index.ts", "source_location": "155", "source_url": null, "captured_at": null, "author": null, "contributor": null}, {"id": "typesindex_monthlybudget", "label": "MonthlyBudget type", "file_type": "code", "source_file": "src/types/index.ts", "source_location": "88", "source_url": null, "captured_at": null, "author": null, "contributor": null}, {"id": "typesindex_monthlybudgetitem", "label": "MonthlyBudgetItem type", "file_type": "code", "source_file": "src/types/index.ts", "source_location": "99", "source_url": null, "captured_at": null, "author": null, "contributor": null}, {"id": "typesindex_settings", "label": "Settings type", "file_type": "code", "source_file": "src/types/index.ts", "source_location": "14", "source_url": null, "captured_at": null, "author": null, "contributor": null}], "edges": [], "hyperedges": []}